[
  {
    "message": "［智樹］：ふん、シッポを巻いて逃げたのかと思ったよ。"
  },
  {
    "message": "［優馬］：……。"
  },
  {
    "message": "フロントガラスに夕日が反射し、はっきり見えたわけではなかった。しかし何となく感じていた嫌な予感が、そのまま現実となる。"
  },
  {
    "message": "［杏奈］：稲垣さん、忙しかったの？"
  },
  {
    "message": "［智樹］：稲垣？"
  },
  {
    "message": "［杏奈］：うん、てっきり稲垣さんが来るかと思った。"
  },
  {
    "message": "［智樹］：迎えに来る車がどこにある？"
  },
  {
    "message": "［杏奈］：……え？"
  },
  {
    "message": "［智樹］：お前な、今と昔の河原崎家は違うんだよ。自分好みの使用人を何人も使い、道楽で子供を引き取っていた、あの河原崎家とはな……。"
  },
  {
    "message": "やつの一語一句が俺の神経を逆撫でする。この横柄な口調で、今まで無事に生きてこられた事が不思議でならない。"
  },
  {
    "message": "自分の事であれば我慢もできるが、侮辱する相手が杏奈なら話は別だ。俺は拳を握りしめたまま、ずいっと前へ進み出た。"
  },
  {
    "message": "［優馬］：お前って誰の事だ？"
  },
  {
    "message": "［智樹］：杏奈の事さ。"
  },
  {
    "message": "［優馬］：お前じゃなくて杏奈さん、だろ？"
  },
  {
    "message": "［智樹］：まるで彼女を守る家来って感じだな……え？"
  },
  {
    "message": "［優馬］：せめて名前で呼べよ。"
  },
  {
    "message": "［智樹］：ふふん、あんたにそんな事を言われる筋合いはない。僕はあんたより、ずっとずっと昔から杏奈の事を知ってるんだから。"
  },
  {
    "message": "知っているから何だと言うのだろう。喧嘩などロクにした事もない俺だが、ここで引き下がるわけにはいかない。"
  },
  {
    "message": "［杏奈］：喧嘩はもうおしまい。"
  },
  {
    "message": "険悪な空気の隙間に杏奈がすっと腕を入れてくる。"
  },
  {
    "message": "［杏奈］：暴力をふるうと、手が痛くなるよ。"
  },
  {
    "message": "［優馬］：……。"
  },
  {
    "message": "その言い方が妙におかしかった。そして諭すような彼女の視線が、俺の心にプスリと穴を開ける。"
  },
  {
    "message": "戦意の萎えた俺は視線を智樹から逸らした。彼女の言うとおり、こんな野郎を殴っても己の手が痛くなるだけだ。"
  },
  {
    "message": "［智樹］：ふん、その程度の事で収まる怒りか……くだらない。"
  },
  {
    "message": "俺はその言葉を完全に無視すると、すたすたと車のほうへ歩き始める。智樹の事は、礼儀を知らないただの運転手だと思えばいい。"
  },
  {
    "message": "［智樹］：杏奈は前で、あんたは後ろの席だ。"
  },
  {
    "message": "そう言うと智樹は不機嫌そうに運転席へ乗り込む。"
  },
  {
    "message": "［杏奈］：ありがと。"
  },
  {
    "message": "［優馬］：……え？"
  },
  {
    "message": "［杏奈］：我慢してくれて。"
  },
  {
    "message": "［優馬］：杏奈が止めてくれたから。"
  },
  {
    "message": "［杏奈］：……。"
  },
  {
    "message": "［智樹］：いつまで待たせるつもりだ！！"
  },
  {
    "message": "車の窓から身を乗り出して智樹が怒鳴っている。"
  },
  {
    "message": "［杏奈］：（……車だからすぐ着くよ）"
  },
  {
    "message": "杏奈が俺だけにしか聞こえないような小声で囁いた。たぶん彼女は、自分が智樹の隣へ座る事を気遣ってくれたのだろう。"
  },
  {
    "message": "［杏奈］：行こ？"
  },
  {
    "message": "［優馬］：うん……。"
  },
  {
    "message": "杏奈が俺の手をぎゅっと握る。"
  },
  {
    "message": "［智樹］：早くしろ！！"
  },
  {
    "message": "クラクションを鳴らし苛立たしげに声を張り上げる智樹。しかし杏奈に手を握られていると、やつの横柄さを余裕で受け流す事ができる。"
  },
  {
    "message": "杏奈が智樹の隣に座ろうと、彼女の恋人はこの俺なのだ。これだけは、天と地が入れ替わろうと変わらない。"
  }
]