[
  {
    "message": "［優馬］：あ……。"
  },
  {
    "message": "［真樹］：お兄ちゃ～ん。"
  },
  {
    "message": "俺を置き去りにして扉を叩き始める真樹。たぶん一緒にいる事で、智樹から文句を言われるのが嫌なのだろう。"
  },
  {
    "message": "［真樹］：お兄ちゃん、いないの～？"
  },
  {
    "message": "［智樹］：なんだ、また具合でも悪くなったのか？"
  },
  {
    "message": "［真樹］：違うよ。"
  },
  {
    "message": "［智樹］：……ノックは一回で十分だ。"
  },
  {
    "message": "［真樹］：ご、ごめん……。"
  },
  {
    "message": "［智樹］：真樹、どうしてノブを引っ張る。"
  },
  {
    "message": "［真樹］：へ、部屋から出なくていいってば～。"
  },
  {
    "message": "［智樹］：ふん、こういう事か……。"
  },
  {
    "message": "［優馬］：……。"
  },
  {
    "message": "こうなったら直接やつに聞いてやればいい。"
  },
  {
    "message": "［優馬］：なあ、奈津子さんと一緒だった男の人を覚えてるだろ。"
  },
  {
    "message": "［智樹］：本当にお前はしつこいやつだな。悪いのは写真機を向けたあいつだ……偶然だろうがそんな事は関係ない。"
  },
  {
    "message": "［真樹］：ち、違うよぉ、お兄ちゃん……ゆーまさんは……。"
  },
  {
    "message": "［智樹］：真樹、お前は黙ってろ。"
  },
  {
    "message": "［真樹］：……は～い。"
  },
  {
    "message": "［智樹］：いいか、これ以上僕や真樹にまとわりつくな。屋敷に戻り歓迎されたのは杏奈であって、お前じゃない。"
  },
  {
    "message": "［智樹］：いいか、これ以上僕や真樹にまとわりつくな。屋敷に留まる事を歓迎されたのは杏奈であって、お前じゃない。"
  },
  {
    "message": "［優馬］：……。"
  },
  {
    "message": "［真樹］：ご、ごめん。"
  },
  {
    "message": "［優馬］：気にしてないからいいって。"
  },
  {
    "message": "［真樹］：真樹は、ゆーまさんの事も大歓迎してるよ。"
  },
  {
    "message": "［優馬］：……ありがとう。"
  },
  {
    "message": "彼女なりに気を遣ってくれてるのだろう。もちろんその言葉が嘘というわけではなく、そう言わずにはいられなかったという意味だ。"
  },
  {
    "message": "［優馬］：あの様子だと智樹は何も知らないみたいだし……。"
  },
  {
    "message": "［真樹］：うん、部屋にもお兄ちゃんしかいなかった。ゆーまさん、今度はどこを探そうか。"
  },
  {
    "message": "［優馬］：……。"
  },
  {
    "message": "思いつく限り考えはしたが、他に探す場所が見つからない。"
  },
  {
    "message": "［優馬］：一度ホールに戻ろう。"
  },
  {
    "message": "［真樹］：うん、たぶん杏奈さん達が見つけてると思う。二階にその人がいないなら、あとは一階しかないもん……ね？"
  },
  {
    "message": "［優馬］：……。"
  },
  {
    "message": "スカートの裾を揺らしながら跳ねるように歩く真樹。彼女は途中何度も振り返りながら、俺がついてくるか確認していた。"
  }
]