[
  {
    "message": "［真樹］：やった、真樹が一等しょ～。"
  },
  {
    "message": "［優馬］：ひ、一人で先に行ったらダメだってば。"
  },
  {
    "message": "［真樹］：へへーっ、ごめん。"
  },
  {
    "message": "謝りつつ真樹はまったく悪びれた様子を見せない。彼女は昨晩と似た状況がよほど嬉しいのか、その場で飛び跳ねながらベッドを指さした。"
  },
  {
    "message": "［真樹］：真樹、昨日と同じ場所ね～。"
  },
  {
    "message": "［優馬］：あ……。"
  },
  {
    "message": "［杏奈］：奈津子さんもいいかな。少し疲れてるみたいだし。"
  },
  {
    "message": "［優馬］：うん、奈津子さんだけじゃなく杏奈も。"
  },
  {
    "message": "［杏奈］：……ありがとう。"
  },
  {
    "message": "［真樹］：またシリトリでもする～？"
  },
  {
    "message": "［優馬］：真樹ちゃん、奈津子さんの彼がまだ見つかってないから……。"
  },
  {
    "message": "［真樹］：あ、そっか……奈津子さん、ごめん。"
  },
  {
    "message": "［奈津子］：……。"
  },
  {
    "message": "たぶん俺達を気遣い無理に微笑んでるのだろう。それでもやはり、奈津子の表情は心ここにあらずといった感じだ。"
  },
  {
    "message": "窓の外はとっくに帳が下りている。いくら落ち着きを取り戻したとはいえ、彼女が平静でいられるわけもない。"
  },
  {
    "message": "［奈津子］：……日が暮れちゃったね。"
  },
  {
    "message": "［優馬］：うん……。"
  },
  {
    "message": "［奈津子］：健吾君、どこにいるんだろう……。"
  },
  {
    "message": "［杏奈］：優馬、屋敷の中をもう一度探してみようよ……ね？"
  },
  {
    "message": "［優馬］：そ、そうしようか。"
  },
  {
    "message": "もちろん今の返事は奈津子に対する気休めでしかない。間違いなく健吾は、俺が中庭を走り回っている時に縄綱の部屋へ移されている。"
  },
  {
    "message": "おぞましい記憶が脳裏に蘇り、思わず俺は身体を震わせた。しかし奈津子がここにいる限り、健吾も過剰な危害は加えられないはずだ。"
  },
  {
    "message": "もちろん今の返事は奈津子に対する気休めでしかない。俺の予想だと、健吾はすでに縄綱の部屋へ移されているはずだ。"
  },
  {
    "message": "そして呼び出された奈津子は健吾と引き合わされる。だからあの時、彼女は稲垣達の命令に従うしかなかった……。"
  },
  {
    "message": "［優馬］：……？"
  },
  {
    "message": "扉を叩く音に俺は慌てて振り向く。健吾が行方知れずである以上、無視するわけにもいかない。"
  },
  {
    "message": "案の定、ハッと顔を上げた奈津子がベッドから立ち上がった。身に迫る危険を知らない彼女にすれば、どんな些細な情報でも欲しいだろう。"
  },
  {
    "message": "［奈津子］：も、もしかしたら……。"
  },
  {
    "message": "［優馬］：俺が出るから奈津子さんは座ってて……ね？"
  },
  {
    "message": "［奈津子］：で、でも……私……。"
  },
  {
    "message": "［杏奈］：……。"
  },
  {
    "message": "察した杏奈が奈津子の肩にそっと手をかける。杏奈は安心させるよう優しく微笑み、続けて俺の顔を見ながら小さく頷く。"
  },
  {
    "message": "再びベッドへ腰掛けた奈津子は落ち着かない様子だ。もちろん健吾がここへ来るわけもなく、開く扉の隙間は最小限に留めようと心掛ける。"
  },
  {
    "message": "［稲垣］：おや、どうして扉を閉めるのでしょう。"
  },
  {
    "message": "［優馬］：っ……。"
  },
  {
    "message": "扉の隙間からやつの顔が見えた時、俺は反射的に廊下へ出てしまった。"
  },
  {
    "message": "［優馬］：何か用？"
  },
  {
    "message": "［稲垣］：奈津子様はいらっしゃいますか？"
  },
  {
    "message": "［優馬］：いるけど具合が悪そうなんだ。午後から屋敷中を探し回って、結局見つからなかったし……だから俺が代わりに聞くよ。"
  },
  {
    "message": "［稲垣］：できたら直接お伝えしたほうがよろしいかと。朗報でございますので、元気も出ると思われますが……。"
  },
  {
    "message": "［優馬］：まさか、健吾さんが見つかったとか？"
  },
  {
    "message": "［稲垣］：……はい。"
  },
  {
    "message": "［優馬］：じゃあ、今すぐここへ連れて来てよ。"
  },
  {
    "message": "［稲垣］：それは無理でございましょう。健吾様は山の中を迷われておりましたから、今はご主人様の部屋で静養されております。"
  },
  {
    "message": "［優馬］：……。"
  },
  {
    "message": "［稲垣］：直接お伝えできない事を稲垣は了承致しました。ならば今度は、優馬様が稲垣の申し出を受け入れる番でございますよ。"
  },
  {
    "message": "［優馬］：どういう意味？"
  },
  {
    "message": "［稲垣］：ご主人様の部屋へ来るよう、奈津子様にお伝えください。今夜は時間も遅く、お二人でお泊まりする客室をご用意致しますので……。"
  },
  {
    "message": "［優馬］：っ……。"
  },
  {
    "message": "表情一つ変えない稲垣。しかし思う通り事を運ばせない俺の存在が、やつの腸を煮え繰り返らせているに違いない。"
  },
  {
    "message": "俺はどう伝えるか迷いながら扉のほうを振り向いた。まさか奈津子へ何も伝えないわけにもいかず、まして稲垣の声が届いてる可能性だってある。"
  },
  {
    "message": "［奈津子］：……け、健吾君の事？"
  },
  {
    "message": "［優馬］：っ……聞こえたの？"
  },
  {
    "message": "［奈津子］：ううん、でも稲垣さんが来た事はわかった。もし健吾君の話なら私に教えて。"
  },
  {
    "message": "［優馬］：……見つかったみたいだから、俺が迎えに行ってくるよ。"
  },
  {
    "message": "［奈津子］：ほ、本当に？"
  },
  {
    "message": "［優馬］：ああ、だから奈津子さんはここで待ってて。俺、稲垣さんからそう言われてるし……。"
  },
  {
    "message": "［奈津子］：そ、そんな……。"
  },
  {
    "message": "［優馬］：……。"
  },
  {
    "message": "どう考えても奈津子を一人で行かせるのはまずい。彼女が納得してくれなくても、この考えを譲るわけにいかない。"
  },
  {
    "message": "一人で行けばまず無事には済まないだろう。やつから脅され、健吾の命と引き換えにおぞましい屈辱を与えられるのだ。"
  },
  {
    "message": "［杏奈］：奈津子さんが一緒だとダメなの？"
  },
  {
    "message": "［優馬］：……。"
  },
  {
    "message": "［杏奈］：……？"
  },
  {
    "message": "［優馬］：杏奈……。"
  },
  {
    "message": "［杏奈］：なに？"
  },
  {
    "message": "［優馬］：……俺じゃないとダメなんだ。"
  },
  {
    "message": "［杏奈］：わかった、それなら私達はここでお留守番をしてる。奈津子さんの事は何も心配しなくていいよ……私にまかせて。"
  },
  {
    "message": "［優馬］：あ、ありがと。"
  },
  {
    "message": "［真樹］：じゃあ、真樹が一緒に行く～。"
  },
  {
    "message": "［優馬］：え？"
  },
  {
    "message": "［真樹］：真樹が一緒じゃだめ～？"
  },
  {
    "message": "［優馬］：へ、部屋にいたほうが楽しいと思うけど。"
  },
  {
    "message": "［真樹］：んー、真樹にも色々と都合があるってわけ。"
  },
  {
    "message": "［優馬］：？？？"
  },
  {
    "message": "［真樹］：ね～、一緒に行っていいよね……真樹、邪魔しないからさ。"
  },
  {
    "message": "真樹を連れて行く"
  },
  {
    "message": "そんな事は無理だ"
  },
  {
    "message": "真樹を連れて行く"
  },
  {
    "message": "そんな事は無理だ"
  },
  {
    "message": "［優馬］：……いいよ。"
  },
  {
    "message": "［奈津子］：ど、どうして？"
  },
  {
    "message": "［真樹］：わーい、良かった～。"
  },
  {
    "message": "［優馬］：……無理だよ。"
  },
  {
    "message": "［真樹］：ぷ～、どうして～？"
  },
  {
    "message": "［優馬］：杏奈、俺が出たら鍵をかけておいてくれ。"
  },
  {
    "message": "［真樹］：そんな事したって無駄だよ～、だ。"
  },
  {
    "message": "［優馬］：っ……。"
  }
]