[
  {
    "message": "［真樹］：あ……。"
  },
  {
    "message": "［杏奈］：優馬っ！！"
  },
  {
    "message": "［智樹］：ま、待て、杏奈っ。"
  },
  {
    "message": "［杏奈］：智樹君っ、放して……お願いっ。"
  },
  {
    "message": "［優馬］：みんな……逃げ……ろ……。"
  },
  {
    "message": "［縄綱］：……稲垣はどこかね？"
  },
  {
    "message": "［智樹］：し、知るもんか。"
  },
  {
    "message": "［縄綱］：智樹や、そんな冷たい言い方をしないでおくれ。それでなくても縄綱は寂しい思いをしておるのだ。"
  },
  {
    "message": "［縄綱］：誰も縄綱の誕生日を祝ってくれぬ。これではお前達を呼び寄せた意味もなくなり、願いが一つも成就せぬまま、夜明けを迎えてしまう……。"
  },
  {
    "message": "［杏奈］：っ……優馬を放してください。"
  },
  {
    "message": "［縄綱］：よいか、全ての元凶はこの男にあるのだよ。小狡く我が思惑の先回りをし、宴の邪魔ばかりしおる。"
  },
  {
    "message": "［杏奈］：優馬は何も悪い事をしてませんっ。おかしいのは叔父様達で、優馬じゃありませんっ。"
  },
  {
    "message": "［縄綱］：おお、怒った顔の何と美しい事か。お前は本当に母親と瓜二つの表情をしおる……見ているだけで我が細胞も若返ってくるわ。"
  },
  {
    "message": "［杏奈］：お、お母さん……？"
  },
  {
    "message": "［縄綱］：こやつの命が惜しければ、みんな書斎に集まるがいい。まずは真樹に我がペニスをしゃぶらせ、代わりに杏奈の肛門を舐めてやろう。"
  },
  {
    "message": "［杏奈］：っ……いやらしい。"
  },
  {
    "message": "［真樹］：ペニスぅ？"
  },
  {
    "message": "［縄綱］：そして智樹はそれを眺めながら、奈津子の膣を蹂躙してやるのだ。ああ、なんと素晴らしい光景……なんと素敵な家族愛……。"
  },
  {
    "message": "［智樹］：こ、このキチガイめ。"
  },
  {
    "message": "［縄綱］：むう、奈津子で不満なら鈴音を分け与えても良いぞ。あの女はこの日の為に、破瓜を免れておる……智樹や、鈴音の性器を想像するのだ。"
  },
  {
    "message": "［智樹］：う……。"
  },
  {
    "message": "［縄綱］：くくっ、どんな割れ目をしてると思うかね？"
  },
  {
    "message": "［智樹］：ぼ、僕は鈴音なんかに興味はない。"
  },
  {
    "message": "［縄綱］：そうか、ならば杏奈に奉仕を命じてやろう。縄綱が見ている事を条件とするなら、お前の好きにする事だってできる。"
  },
  {
    "message": "［縄綱］：ほれ、杏奈の乳房と性器を想像するのだ。こんな馬鹿の言う事に惑わされず、今より河原崎家の一員に戻れ……。"
  },
  {
    "message": "［杏奈］：……と、智樹君。"
  },
  {
    "message": "［智樹］：だ、大丈夫だ……はあはあっ……僕は、平気だ。"
  },
  {
    "message": "［縄綱］：ならばこうしてやろう。"
  },
  {
    "message": "［優馬］：くっ……。"
  },
  {
    "message": "［縄綱］：いくら首の間に指を入れても同じ事。もっとも息を詰まらせる前に、自重で骨が抜けてしまうかも知れぬぞ……。"
  },
  {
    "message": "［杏奈］：やめて～っ！！"
  },
  {
    "message": "［優馬］：ぐ……ぅ……っ……。"
  },
  {
    "message": "［縄綱］：ほれ、だんだん目玉が飛び出してきたわ。そのうち穴という穴から、体液が流れ出てくる……杏奈、お前はこの男を見殺しにするのかね？"
  },
  {
    "message": "［杏奈］：わ、私……。"
  },
  {
    "message": "［縄綱］：智樹はもはや縄綱に抗う勇気などない。この男を助けられるかどうかは、お前の判断一つにかかっておる。"
  },
  {
    "message": "［杏奈］：私、叔父様と一緒に……。"
  },
  {
    "message": "［＊＊＊］：い、言う事を聞いたらだめです。"
  },
  {
    "message": "［杏奈］：あっ！！"
  },
  {
    "message": "［優馬］：ごほっ、ごほっ……す、鈴音さん……。"
  },
  {
    "message": "［杏奈］：優馬っ、大丈夫！？"
  },
  {
    "message": "［優馬］：あ、ああ……ごほっ……げほっ……っ。"
  },
  {
    "message": "［真樹］：死んじゃったのぉ？"
  },
  {
    "message": "［鈴音］：わ、私はそんなつもりじゃ……。"
  },
  {
    "message": "［智樹］：っ、こんな酷いやつを殺しても罪になるか。鈴音、何かあったら僕が証人になってやるっ。"
  },
  {
    "message": "［鈴音］：は、はい。"
  },
  {
    "message": "智樹の言葉に何故かみんなまで元気づけられた。引きつっていた顔もどこかほっとした感じで、何より嬉しいのはその中に鈴音も含まれている事だ。"
  },
  {
    "message": "［優馬］：な、奈津子さん達は……。"
  },
  {
    "message": "［鈴音］：……お二人ともご主人様の部屋です。"
  },
  {
    "message": "［優馬］：っ、じゃあ……。"
  },
  {
    "message": "未だ詰まる喉に言葉がうまく出てこない。それでも風向きが変わった勢いに助けられ、俺は何とか声を振り絞る事ができた。"
  },
  {
    "message": "自分と真樹が縄綱を見張り奈津子達の事はまかせる"
  },
  {
    "message": "智樹と真樹に縄綱を見張らせ自ら奈津子達を助ける"
  },
  {
    "message": "自分と真樹が縄綱を見張り奈津子達の事はまかせる"
  },
  {
    "message": "智樹と真樹に縄綱を見張らせ自ら奈津子達を助ける"
  },
  {
    "message": "［優馬］：智樹、俺と真樹ちゃんで縄綱を見張っている。鈴音さん、杏奈と智樹を奈津子さん達がいるところへ……。"
  },
  {
    "message": "［智樹］：も、もし美香がいたらどうするんだよ。"
  },
  {
    "message": "［優馬］：お前のスコップはただの飾りなのか？"
  },
  {
    "message": "［智樹］：っ……。"
  },
  {
    "message": "［鈴音］：あの、たぶん美香さんは屋敷に戻ってないです。私、ホールへ出入りする人を見張るよう言われてましたから……。"
  },
  {
    "message": "［杏奈］：わかった……行こう、智樹君。"
  },
  {
    "message": "［智樹］：あ、ああ……。"
  },
  {
    "message": "［優馬］：や、屋敷へ戻ってないって……厨房にも来なかったの？"
  },
  {
    "message": "［鈴音］：は、はい……一度も。"
  },
  {
    "message": "［優馬］：じゃあ、冷蔵庫の中に……。"
  },
  {
    "message": "［鈴音］：……？"
  },
  {
    "message": "［優馬］：……。"
  },
  {
    "message": "記憶に残る美香はもうどこにも存在していないらしい。そう、未来が変われば当然彼女の行動も変化する。"
  },
  {
    "message": "しかしどうなろうとその思惑だけは不変だろう。あの女の忠誠はあくまで自分が楽しむ為のもので、たぶん今回も一人で逃げようとするに違いない。"
  },
  {
    "message": "［杏奈］：……行こう、智樹君。"
  },
  {
    "message": "［智樹］：あ、ああ……。"
  },
  {
    "message": "［優馬］：智樹、真樹ちゃんと一緒に縄綱を見張っててくれ。鈴音さん、俺と杏奈を奈津子さん達がいるところへ……。"
  },
  {
    "message": "［鈴音］：は、はい。"
  },
  {
    "message": "［智樹］：おいっ、もし美香が来たらどうするんだよ。"
  },
  {
    "message": "［優馬］：お前のスコップはただの飾りなのか？"
  },
  {
    "message": "［智樹］：っ……何だと？"
  },
  {
    "message": "［鈴音］：あの、たぶん美香さんは屋敷にいないと思います。私、ホールへ出入りする人を見張るよう言われてましたから……。"
  },
  {
    "message": "［智樹］：ちっ、それを最初に言えよ。"
  },
  {
    "message": "［優馬］：いないって……いつから？"
  },
  {
    "message": "［鈴音］：奈津子様を連れて来られた時が最後です。そのあと、すぐにまた中庭へ出て行かれました。"
  },
  {
    "message": "［優馬］：厨房にも立ち寄らず？"
  },
  {
    "message": "［鈴音］：は、はい……一度も。"
  },
  {
    "message": "［優馬］：じゃあ、冷蔵庫の中に鍵は……。"
  },
  {
    "message": "［鈴音］：……？"
  },
  {
    "message": "［優馬］：……。"
  },
  {
    "message": "記憶に残る美香はもうどこにも存在していないらしい。そう、未来が変われば当然彼女の行動も変化する。"
  },
  {
    "message": "しかしどうなろうとその思惑だけは不変だろう。あの女の忠誠はあくまで自分が楽しむ為のもので、たぶん今回も一人で逃げようとするに違いない。"
  },
  {
    "message": "［優馬］：それなら、玄関が開かないよう押さえておけば安心だ……杏奈、行こう。"
  },
  {
    "message": "［杏奈］：う、うん。"
  }
]