[
  {
    "message": "［美香］：あら……。"
  },
  {
    "message": "［優馬］：……。"
  },
  {
    "message": "踊り場にいる時から彼女の姿には気づいていた。まるで誰かが来るのを待っているように、階段の下でただじっと佇んでいた美香……。"
  },
  {
    "message": "［優馬］：ここで何してるんだ？"
  },
  {
    "message": "［美香］：優馬様こそ鈴音に何をしましたの？"
  },
  {
    "message": "［優馬］：さあ、ね。"
  },
  {
    "message": "［美香］：よほど嬉しい事をされたのかしら……あの子、顔を真っ赤にしてましたわ。"
  },
  {
    "message": "［優馬］：……あんたと同じ事をしてやっただけだよ。"
  },
  {
    "message": "［美香］：美香と同じ事……？"
  },
  {
    "message": "［優馬］：いきなり俺にキスしたじゃないか。"
  },
  {
    "message": "［優馬］：叱られないようにしてやっただけだよ。"
  },
  {
    "message": "［美香］：叱られないように……？"
  },
  {
    "message": "［優馬］：あんたはいきなりキスするような女だからな。さぞ鈴音にも酷い叱り方をすると思ってね……つまり彼女を助けてやったわけだ。"
  },
  {
    "message": "［美香］：あれは夢など見てない事をお教えする為ですわ。美香は優馬様の事が大好きですから、お顔を見ただけで考えてる事がわかりますの。"
  },
  {
    "message": "［優馬］：ずいぶん変わった教え方をするんだな。"
  },
  {
    "message": "［美香］：頬を抓るよりマシだと思いますけど……。"
  },
  {
    "message": "［優馬］：……。"
  },
  {
    "message": "本当に嫌な女だと思った。"
  },
  {
    "message": "［美香］：優馬様、どうかこれからも鈴音を可愛がってください。もし粗相をした時は、遠慮せずこの美香に……。"
  },
  {
    "message": "［優馬］：へえ、言うとどうなるんだ？"
  },
  {
    "message": "［美香］：はい、美香が優しく指導致します。"
  },
  {
    "message": "美香がスカートの端を持って慇懃に会釈をする。"
  },
  {
    "message": "［美香］：そうそう、大切な事を言い忘れてましたわ。ようやくお風呂のご用意ができましたの。よろしければ、お先にどうぞ……。"
  },
  {
    "message": "そう言うと美香は階段の裏側へ消えていった。これではまるで、その事を伝える為だけに待っていたようなものだ。"
  },
  {
    "message": "［優馬］：ふん……。"
  },
  {
    "message": "もちろん風呂へ入る気など微塵もなかった。俺はくるりと後ろを向き、美香の言葉など無視するように玄関の扉へと歩み寄った。"
  },
  {
    "message": "たぶん、青白かった顔は赤く火照っているに違いない。そう思えるほど、心臓の鼓動が早鐘のように鳴っている。"
  },
  {
    "message": "［優馬］：……。"
  },
  {
    "message": "そう、この扉を開けば杏奈の引きつった顔を拝む事ができるのだ。逸る気持ちのせいか、把手を握る手にもじっとり汗が滲んでくる……。"
  },
  {
    "message": "［杏奈］：あ……。"
  },
  {
    "message": "座っていた杏奈が驚いたように立ち上がった。"
  },
  {
    "message": "［優馬］：……。"
  },
  {
    "message": "［杏奈］：……優馬？"
  },
  {
    "message": "やはり俺の思ったとおりだ。彼女は強ばる顔を見られないよう、背中を向けたまま振り返ろうとしない。"
  },
  {
    "message": "［杏奈］：星空、綺麗だね……。"
  },
  {
    "message": "［優馬］：……。"
  },
  {
    "message": "一生懸命に誤魔化そうとする杏奈。しかしそのわざとらしい言葉が、ますます俺の怒りを増長させる。"
  },
  {
    "message": "［優馬］：こっちを向けよ。"
  },
  {
    "message": "［杏奈］：……。"
  },
  {
    "message": "［優馬］：……。"
  },
  {
    "message": "［杏奈］：……今は無理みたい。"
  },
  {
    "message": "［優馬］：……無理みたい？"
  },
  {
    "message": "［杏奈］：うん……。"
  },
  {
    "message": "［優馬］：振り向けないのは、引きつった顔を俺に見られたくないからだろ。お前が智樹とここで待ち合わせしてる事は、わかってるんだ。"
  },
  {
    "message": "［杏奈］：智樹君と私が待ち合わせ？"
  },
  {
    "message": "［優馬］：そうだよ、だからお前は俺の部屋から逃げ出した。智樹と逢う前にキスして悪かったな。"
  },
  {
    "message": "［杏奈］：……どうしてそうなっちゃうんだろ。"
  },
  {
    "message": "［優馬］：いつから智樹に気持ちが傾いてたんだ？"
  },
  {
    "message": "［杏奈］：……。"
  },
  {
    "message": "［優馬］：前から、智樹と一緒にいるほうが楽しかったんだろ？"
  },
  {
    "message": "［杏奈］：あのね、優馬……。"
  },
  {
    "message": "［優馬］：ほら、今まで俺に隠れて何をしてきたのかハッキリ言えよ。"
  },
  {
    "message": "［杏奈］：私は……。"
  },
  {
    "message": "［優馬］：キスはもうしたのか？"
  },
  {
    "message": "［杏奈］：……。"
  },
  {
    "message": "［優馬］：（う……）"
  },
  {
    "message": "俺は股間が脈打つのを感じていた。こうして杏奈を責め続けていると、何故か性的に興奮してきてしまう。"
  },
  {
    "message": "［優馬］：たぶん、胸も揉まれたんだろうな。"
  },
  {
    "message": "［杏奈］：もうやめようよ……。"
  },
  {
    "message": "［優馬］：……。"
  },
  {
    "message": "［杏奈］：……。"
  },
  {
    "message": "［優馬］：ああ、お前の言うとおりやめてやるさ……望みどおり、全ておしまいにしてやる。"
  },
  {
    "message": "［杏奈］：……おしまいにする？"
  },
  {
    "message": "［優馬］：二度と俺に近づくなって事だよ。"
  },
  {
    "message": "［杏奈］：……。"
  },
  {
    "message": "［優馬］：二股かけやがって……汚らわしい女め。"
  },
  {
    "message": "［杏奈］：汚らわしい女……。"
  },
  {
    "message": "［優馬］：ああ、視界に入れただけで吐き気がするくらいだ。"
  },
  {
    "message": "［杏奈］：……。"
  },
  {
    "message": "［優馬］：……。"
  },
  {
    "message": "［杏奈］：……わかった。"
  },
  {
    "message": "［優馬］：ふん、せいぜい智樹と仲良くするがいいさ。ただし、このままで済むと思ったら大間違いだからな！！"
  },
  {
    "message": "とうとう俺は杏奈に白状させてやった。"
  },
  {
    "message": "これで智樹と杏奈の関係がはっきりしたわけだ。俺がこれからどんな仕返しをしようと、その責任は全て原因を作ったやつらにある。"
  }
]